MANIFEST.in
README.md
build.py
requirements.txt
setup.py
market_break/backtest.py
market_break/dataset.py
market_break/interval.py
market_break/labels.py
market_break/process.py
python_market_break.egg-info/PKG-INFO
python_market_break.egg-info/SOURCES.txt
python_market_break.egg-info/dependency_links.txt
python_market_break.egg-info/requires.txt
python_market_break.egg-info/top_level.txt