Metadata-Version: 2.1
Name: python-market-break
Version: 3.3.0
Summary: A set of tools to help create algorithmic trading strategies and test them, in a vectorized way.
Home-page: https://github.com/Shahaf-F-S/market-break
Author: Shahaf Frank-Shapir
Author-email: shahaffrs@gmail.com
License: MIT
Classifier: Intended Audience :: Developers
Classifier: License :: OSI Approved :: MIT License
Classifier: Programming Language :: Python
Classifier: Programming Language :: Python :: 3
Classifier: Programming Language :: Python :: 3.12
Classifier: Operating System :: OS Independent
Requires-Dist: numpy>=2.1.3
Requires-Dist: pandas
Requires-Dist: matplotlib
Provides-Extra: dev
